anyscrape/__init__.py
anyscrape/scraper.py
AnyScrape-0.1.2.dist-info/METADATA
AnyScrape-0.1.2.dist-info/WHEEL
AnyScrape-0.1.2.dist-info/top_level.txt
AnyScrape-0.1.2.dist-info/RECORD
